AUTHORS.txt
LICENSE.txt
MANIFEST.in
Makefile
README.rst
autocommit.py
manage.py
setup.py
django_workon.egg-info/PKG-INFO
django_workon.egg-info/SOURCES.txt
django_workon.egg-info/dependency_links.txt
django_workon.egg-info/not-zip-safe
django_workon.egg-info/requires.txt
django_workon.egg-info/top_level.txt
workon/__init__.py
workon/__init__.pyc
workon/conf.py
workon/urls.py
workon/version.py
workon/version.pyc
workon/__pycache__/__init__.cpython-36.pyc
workon/__pycache__/conf.cpython-36.pyc
workon/__pycache__/urls.cpython-36.pyc
workon/__pycache__/version.cpython-36.pyc
workon/contrib/__init__.py
workon/contrib/__pycache__/__init__.cpython-36.pyc
workon/contrib/cleaner/__init__.py
workon/contrib/cleaner/cache.py
workon/contrib/cleaner/cleanup.py
workon/contrib/cleaner/handlers.py
workon/contrib/cleaner/signals.py
workon/contrib/cleaner/__pycache__/__init__.cpython-36.pyc
workon/contrib/cleaner/__pycache__/cache.cpython-36.pyc
workon/contrib/cleaner/__pycache__/handlers.cpython-36.pyc
workon/contrib/cleaner/__pycache__/signals.cpython-36.pyc
workon/contrib/tracker/__init__.py
workon/contrib/tracker/models.py
workon/contrib/tracker/utils.py
workon/contrib/tracker/__pycache__/__init__.cpython-36.pyc
workon/contrib/tracker/__pycache__/models.cpython-36.pyc
workon/contrib/tracker/__pycache__/utils.cpython-36.pyc
workon/contrib/tracker/__pycache__/views.cpython-36.pyc
workon/contrib/tracker/migrations/0001_initial.py
workon/contrib/tracker/migrations/__init__.py
workon/contrib/tracker/migrations/__pycache__/0001_initial.cpython-36.pyc
workon/contrib/tracker/migrations/__pycache__/__init__.cpython-36.pyc
workon/fields/__init__.py
workon/fields/array.py
workon/fields/code.py
workon/fields/color.py
workon/fields/date.py
workon/fields/embed.py
workon/fields/file.py
workon/fields/html.py
workon/fields/icon.py
workon/fields/image.py
workon/fields/json.py
workon/fields/media.py
workon/fields/percent.py
workon/fields/phone.py
workon/fields/price.py
workon/fields/tree.py
workon/fields/__pycache__/__init__.cpython-36.pyc
workon/fields/__pycache__/array.cpython-36.pyc
workon/fields/__pycache__/code.cpython-36.pyc
workon/fields/__pycache__/color.cpython-36.pyc
