Metadata-Version: 1.1
Name: django-workon
Version: 1.3.0
Summary: Django extensions packages
Home-page: http://github.com/workon-io/django-workon
Author: Autrusseau Damien
Author-email: autrusseau.damien@gmail.com
License: MIT
Platform: UNKNOWN
Classifier: Development Status :: 5 - Production/Stable
Classifier: Environment :: Web Environment
Classifier: Intended Audience :: Developers
Classifier: License :: OSI Approved :: BSD License
Classifier: Operating System :: OS Independent
Classifier: Programming Language :: Python
Classifier: Framework :: Django
